mkdocs_siemens/__init__.py
mkdocs_siemens-0.0.2.dist-info/LICENSE
mkdocs_siemens-0.0.2.dist-info/METADATA
mkdocs_siemens-0.0.2.dist-info/WHEEL
mkdocs_siemens-0.0.2.dist-info/RECORD
